MANIFEST.in
README.md
setup.py
ssht00ls/.version
ssht00ls/__init__.py
ssht00ls/__main__.py
ssht00ls.egg-info/PKG-INFO
ssht00ls.egg-info/SOURCES.txt
ssht00ls.egg-info/dependency_links.txt
ssht00ls.egg-info/not-zip-safe
ssht00ls.egg-info/top_level.txt
ssht00ls/classes/__init__.py
ssht00ls/classes/agent/__init__.py
ssht00ls/classes/aliases/__init__.py
ssht00ls/classes/client/__init__.py
ssht00ls/classes/config/__init__.py
ssht00ls/classes/connections/__init__.py
ssht00ls/classes/exceptions/__init__.py
ssht00ls/classes/installation/__init__.py
ssht00ls/classes/keys/__init__.py
ssht00ls/classes/scp/__init__.py
ssht00ls/classes/smartcards/__init__.py
ssht00ls/classes/smb/__init__.py
ssht00ls/classes/ssh/__init__.py
ssht00ls/classes/ssh/tunnel.py
ssht00ls/classes/ssh/utils.py
ssht00ls/classes/sshd/__init__.py
ssht00ls/classes/sshfs/__init__.py
ssht00ls/classes/ssync/__init__.py
ssht00ls/classes/ssync/daemons.py
ssht00ls/classes/ssync/index.py
ssht00ls/classes/ssync/utils.py
ssht00ls/classes/utils/__init__.py
ssht00ls/classes/webserver/__init__.py
ssht00ls/lib/opensc/macos/opensc-pkcs11.so
ssht00ls/lib/utils/.version
ssht00ls/lib/utils/handler
ssht00ls/lib/utils/isdir
ssht00ls/lib/utils/log
ssht00ls/lib/utils/size
ssht00ls/static/media/icons/.DS_Store
ssht00ls/static/media/icons/Icon
ssht00ls/static/media/icons/folder.icns
ssht00ls/static/media/icons/folder.png
ssht00ls/static/media/icons/mounted.1.icns
ssht00ls/static/media/icons/mounted.1png.png
ssht00ls/static/media/icons/mounted.paint
ssht00ls/static/media/icons/mounted.png