Metadata-Version: 1.0
Name: ssht00ls
Version: 3.32.2
Summary: Some description.
Home-page: http://github.com/vandenberghinc/ssht00ls
Author: Daan van den Bergh
Author-email: vandenberghinc.contact@gmail.com
License: MIT
Platform: UNKNOWN
